pytest_rerun_all/__init__.py
pytest_rerun_all/plugin.py
pytest_rerun_all-0.1.1.dist-info/LICENSE
pytest_rerun_all-0.1.1.dist-info/METADATA
pytest_rerun_all-0.1.1.dist-info/WHEEL
pytest_rerun_all-0.1.1.dist-info/entry_points.txt
pytest_rerun_all-0.1.1.dist-info/RECORD
