Metadata-Version: 2.1
Name: pytest-rerun-all
Version: 0.1.1
Summary: Rerun testsuite for a certain time or iterations
Home-page: https://github.com/TBxy/pytest-rerun-all
License: MIT
Author: tb
Author-email: tb@wodore.com
Requires-Python: >=3.10,<3.14
Classifier: Development Status :: 3 - Alpha
Classifier: Intended Audience :: Developers
Classifier: License :: OSI Approved :: MIT License
Classifier: Operating System :: MacOS :: MacOS X
Classifier: Operating System :: Microsoft :: Windows
Classifier: Operating System :: POSIX
Classifier: Programming Language :: Python :: 3
Classifier: Programming Language :: Python :: 3.10
Classifier: Programming Language :: Python :: 3.11
Classifier: Programming Language :: Python :: 3.12
Classifier: Programming Language :: Python :: 3.13
Classifier: Topic :: Software Development :: Libraries
Classifier: Topic :: Software Development :: Testing
Classifier: Topic :: Utilities
Requires-Dist: dateparser (>=1.1,<2.0)
Requires-Dist: pytest (>=7.0.0)
Project-URL: Changelog, https://github.com/TBxy/pytest-rerun-all/blob/main/CHANGELOG.md
Project-URL: Issues, https://github.com/TBxy/pytest-rerun-all/issues
Project-URL: Repository, https://github.com/TBxy/pytest-rerun-all
